{
  "programs": [
    {
      "id": "nims_junior",
      "name": "NIMSジュニア研究員制度",
      "name_en": "NIMS Junior Researcher Program",
      "organization": "NIMS（物質・材料研究機構）",
      "description": "NIMSで学位取得のための研究を行う大学院生を任期制職員として雇用する制度。奨学金ではなく雇用形態。NIMS連携大学院（筑波大、北大、東京科学大、横国大、早稲田、阪大、九大）に在籍する学生が対象。",
      "target_nationality": [
        "japanese",
        "foreign"
      ],
      "current_education": [
        "bachelor",
        "master"
      ],
      "desired_path": [
        "master",
        "doctor"
      ],
      "tsukuba_related": true,
      "tsukuba_degree": [
        "master",
        "doctor"
      ],
      "benefits": {
        "博士前期課程（修士）月額": "約160,000円（月11日勤務）",
        "博士後期課程（博士）月額": "約200,000円（月14日勤務）",
        "スタート支援金": "30万円（1回のみ）",
        "保険": "労災保険加入"
      },
      "duration": {
        "修士": "最長2年",
        "博士": "最長3年"
      },
      "required_documents": [
        "申請書（指定word様式）",
        "履歴書（指定excel様式）",
        "成績証明書（博士後期課程の申請者は、学士と修士の両方）",
        "2年以内に受験したTOEIC L&R・TOEFL iBT・IELTS academicいずれかのスコア証明書の写し"
      ],
      "application_schedule": [
        {
          "intake": "2026年度 第1次公募",
          "application_start": "2026年4月1日",
          "deadline": "2026年5月28日",
          "document_screening": "6月中旬",
          "university_recommendation": "7月中旬",
          "exam_date": "8月下旬",
          "first_result": "9月中旬",
          "second_result": "2027年2月中旬",
          "adoption_date": "2027年4月",
          "note": "筑波大学連携大学院向け"
        },
        {
          "intake": "2026年度 第2次公募",
          "application_start": "2026年9月1日",
          "deadline": "2026年10月22日",
          "document_screening": "11月下旬",
          "university_recommendation": "11月下旬～12月上旬",
          "exam_date": "2027年1月下旬",
          "first_result": "2027年2月中旬",
          "adoption_date": "2027年4月または2027年10月",
          "note": "筑波大学連携大学院向け"
        },
        {
          "intake": "2027年3月公募（MI）",
          "application_start": "2027年3月3日",
          "deadline": "2027年4月14日",
          "document_screening": "4月下旬",
          "interview": "5月中旬",
          "first_result": "5月下旬～6月上旬",
          "second_result": "7月中旬",
          "adoption_date": "2026年10月または2027年4月",
          "note": "国際マテリアルズイノベーション学位プログラム向け"
        },
        {
          "intake": "2026年7月公募（MI）",
          "application_start": "2026年7月1日",
          "deadline": "2026年7月30日",
          "document_screening": "8月上旬",
          "interview": "8月中下旬",
          "first_result": "8月下旬～9月上旬",
          "second_result": "10月下旬",
          "adoption_date": "2027年4月または2027年10月",
          "note": "国際マテリアルズイノベーション学位プログラム向け"
        }
      ],
      "url": "https://www.nims.go.jp/hr-development/junior-researcher.html",
      "related_urls": [
        {
          "label": "NIMS大学院プログラム",
          "url": "https://www.nims.go.jp/students/"
        },
        {
          "label": "申請方法",
          "url": "https://www.nims.go.jp/students/how/"
        },
        {
          "label": "筑波大学NIMS連携",
          "url": "https://www.nims.go.jp/tsukuba/en/junior/"
        }
      ],
      "additional_urls": [
        "https://www.nims.go.jp/tsukuba/junior/"
      ]
    },
    {
      "id": "nims_internship",
      "name": "NIMSインターンシップ制度",
      "name_en": "NIMS Internship Program",
      "organization": "NIMS（物質・材料研究機構）",
      "description": "国内外の大学・大学院・高専（本科4年次以上）に在籍中の学生を対象としたインターンシップ。NIMS研究者の指導のもとで研究活動を体験できる。",
      "target_nationality": [
        "japanese",
        "foreign"
      ],
      "current_education": [
        "bachelor",
        "master",
        "doctor"
      ],
      "desired_path": [
        "intern"
      ],
      "tsukuba_related": false,
      "benefits": {
        "日当": "NIMS内における審査の結果、優秀と認められる学生には支給",
        "宿泊費": "NIMS内における審査の結果、優秀と認められる学生には支給",
        "航空券および国内交通費": "学部生のみ支給（研究費での受入の場合は個別問い合わせ）"
      },
      "duration": {
        "第1次公募": "4月〜翌年3月の間で連続90日以内",
        "第2次公募": "7月〜翌年3月の間で連続30日以内"
      },
      "eligibility": {
        "対象": "大学・大学院・高専（本科4年次以上）在籍者",
        "備考": "大学とNIMSのMOU締結不要。研修期間中に学生であること"
      },
      "required_documents": [
        "NIMSインターンシップ申込書",
        "履歴書",
        "在学証明書（写しでも可、直近3ヶ月以内）",
        "成績証明書（写しでも可、大学院に在学の方は学部課程から現在まで）"
      ],
      "application_schedule": [
        {
          "intake": "2026年度 第1次公募",
          "application_start": "2025年12月頃",
          "deadline": "2026年1月30日（金）厳守",
          "result": "2026年3月頃",
          "internship_period": "2026年4月〜2027年3月（連続90日以内）",
          "note": "NIMS研究者を通じて申請、約100名受入"
        },
        {
          "intake": "2026年度 第2次公募",
          "application_start": "2026年4月頃",
          "deadline": "2026年5月頃",
          "result": "2026年6月頃",
          "internship_period": "2026年7月〜2027年3月（連続30日以内）",
          "note": "短期インターン"
        },
        {
          "intake": "2027年度 第1次公募",
          "application_start": "2026年12月頃",
          "deadline": "2027年1月下旬",
          "result": "2027年3月頃",
          "internship_period": "2027年4月〜2028年3月（連続90日以内）",
          "note": "NIMS研究者を通じて申請"
        }
      ],
      "url": "https://www.nims.go.jp/hr-development/internship.html",
      "related_urls": [
        {
          "label": "FAQ",
          "url": "https://www.nims.go.jp/hr-development/hnp5bq000000b7cq.html"
        },
        {
          "label": "研究者総覧SAMURAI",
          "url": "https://samurai.nims.go.jp/"
        },
        {
          "label": "研究人材育成",
          "url": "https://www.nims.go.jp/hr-development/"
        }
      ]
    },
    {
      "id": "jsps_dc",
      "name": "JSPS特別研究員（DC1・DC2）",
      "name_en": "JSPS Research Fellowship for Young Scientists (DC)",
      "organization": "日本学術振興会（JSPS）",
      "description": "優れた若手研究者に研究に専念する機会を与え、創造性に富んだ研究者の養成を目的とした制度。国籍不問（日本の大学の博士課程に在籍する必要あり）。",
      "target_nationality": [
        "japanese",
        "foreign"
      ],
      "current_education": [
        "bachelor",
        "master"
      ],
      "desired_path": [
        "doctor"
      ],
      "tsukuba_related": false,
      "benefits": {
        "月額（PD）": "362,000円",
        "月額（DC1・DC2）": "227,000円（予定）",
        "研究費": "科学研究費助成事業（特別研究員奨励費）に同時応募が可能"
      },
      "duration": {
        "DC1": "3年間",
        "DC2": "2年間"
      },
      "eligibility": {
        "DC1": "博士課程の在籍期間が12ヶ月未満（3年制の場合）",
        "DC2": "博士課程の在籍期間が12ヶ月以上36ヶ月未満（3年制の場合）"
      },
      "required_documents": [
        "申請書情報（電子申請システムで入力）",
        "申請内容ファイル（研究計画書等）"
      ],
      "application_schedule": [
        {
          "intake": "2027年4月採用（PD・DC1・DC2）",
          "note": "申請機関を通じて電子申請。申請機関ごとのID・パスワード発行および申請書受付期間は各機関で設定されるため、所属機関への確認が必要。"
        }
      ],
      "url": "https://www.jsps.go.jp/j-pd/",
      "related_urls": [
        {
          "label": "募集要項",
          "url": "https://www.jsps.go.jp/j-pd/pd_sin.html"
        },
        {
          "label": "選考日程",
          "url": "https://www.jsps.go.jp/j-pd/pd_nittei.html"
        },
        {
          "label": "申請資格・支給経費",
          "url": "https://www.jsps.go.jp/j-pd/pd_oubo.html"
        }
      ],
      "additional_urls": [
        "https://www.jsps.go.jp/j-pd/pd_nittei.html",
        "https://www.jsps.go.jp/j-pd/pd_sin.html"
      ]
    },
    {
      "id": "jsps_pd",
      "name": "JSPS特別研究員（PD）",
      "name_en": "JSPS Research Fellowship for Young Scientists (PD)",
      "organization": "日本学術振興会（JSPS）",
      "description": "博士号取得者を対象とした特別研究員制度。自由な発想のもとに研究に専念する機会を提供。国籍不問。博士号取得機関とは異なる研究機関への移動が必須。",
      "target_nationality": [
        "japanese",
        "foreign"
      ],
      "current_education": [
        "doctor"
      ],
      "desired_path": [
        "postdoc"
      ],
      "tsukuba_related": false,
      "benefits": {
        "月額（PD）": "362,000円",
        "月額（DC）": "227,000円（予定）"
      },
      "duration": {
        "PD": "3年間"
      },
      "eligibility": {
        "PD": "博士号取得者または取得見込み者（学位取得後5年未満）。採用時に学位取得機関以外の研究機関に移動すること"
      },
      "required_documents": [
        "申請書情報（電子申請システムで入力）",
        "申請内容ファイル",
        "評価書"
      ],
      "application_schedule": [
        {
          "intake": "2027年4月採用（PD）",
          "note": "詳細は募集要項を参照。申請機関ごとの受付期間については各機関へ確認が必要"
        },
        {
          "intake": "2027年4月採用（DC1・DC2）",
          "note": "詳細は募集要項を参照。申請機関ごとの受付期間については各機関へ確認が必要"
        }
      ],
      "url": "https://www.jsps.go.jp/j-pd/",
      "related_urls": [
        {
          "label": "募集要項",
          "url": "https://www.jsps.go.jp/j-pd/pd_sin.html"
        },
        {
          "label": "選考日程",
          "url": "https://www.jsps.go.jp/j-pd/pd_nittei.html"
        },
        {
          "label": "制度概要",
          "url": "https://www.jsps.go.jp/j-pd/pd_gaiyo.html"
        }
      ],
      "additional_urls": [
        "https://www.jsps.go.jp/j-pd/pd_nittei.html",
        "https://www.jsps.go.jp/j-pd/pd_sin.html"
      ]
    },
    {
      "id": "jsps_rpd",
      "name": "JSPS特別研究員（RPD）",
      "name_en": "JSPS Research Fellowship (RPD - Restart Postdoctoral Fellowship)",
      "organization": "日本学術振興会（JSPS）",
      "description": "出産・育児により研究を中断した研究者が、円滑に研究現場に復帰できるよう支援する制度。国籍不問。令和8年度より対象が「小学生以下の子を持つ者」に拡充。",
      "target_nationality": [
        "japanese",
        "foreign"
      ],
      "current_education": [
        "doctor"
      ],
      "desired_path": [
        "postdoc"
      ],
      "tsukuba_related": false,
      "benefits": {
        "月額（PD）": "362,000円",
        "月額（DC）": "227,000円（予定）",
        "研究費": "科学研究費助成事業（特別研究員奨励費）に同時応募が可能"
      },
      "duration": {
        "RPD": "3年間"
      },
      "eligibility": {
        "RPD": "出産・育児により42日以上研究を中断した博士号取得者。小学生以下の子を持つ者が対象（令和8年度より拡充）"
      },
      "required_documents": [
        "申請書（電子申請システム）",
        "申請内容ファイル（研究計画書）",
        "評価書",
        "研究中断に関する証明書類",
        "特別研究員奨励費応募調書"
      ],
      "application_schedule": [
        {
          "intake": "2027年度採用（PD）",
          "note": "令和9(2027)年度採用分"
        },
        {
          "intake": "2027年度採用（DC1）",
          "note": "令和9(2027)年度採用分"
        },
        {
          "intake": "2027年度採用（DC2）",
          "note": "令和9(2027)年度採用分"
        }
      ],
      "url": "https://www.jsps.go.jp/j-pd/",
      "related_urls": [
        {
          "label": "募集要項（RPD）",
          "url": "https://www.jsps.go.jp/j-pd/rpd_sin.html"
        },
        {
          "label": "制度概要（RPD）",
          "url": "https://www.jsps.go.jp/j-pd/rpd_gaiyo.html"
        }
      ],
      "additional_urls": [
        "https://www.jsps.go.jp/j-pd/pd_nittei.html",
        "https://www.jsps.go.jp/j-pd/rpd_sin.html"
      ]
    },
    {
      "id": "jsps_foreign",
      "name": "JSPS外国人特別研究員",
      "name_en": "JSPS Postdoctoral Fellowship for Foreign Researchers",
      "organization": "日本学術振興会（JSPS）",
      "description": "諸外国の優秀な若手研究者を日本の大学等に受け入れ、日本側研究者との共同研究を行う機会を提供。一般プログラムと欧米短期プログラムがある。",
      "target_nationality": [
        "foreign"
      ],
      "current_education": [
        "doctor"
      ],
      "desired_path": [
        "postdoc"
      ],
      "tsukuba_related": false,
      "benefits": {
        "滞在費（一般）": "月額362,000円",
        "滞在費（欧米短期・ASEAN/アフリカ短期・博士号取得者）": "月額362,000円",
        "滞在費（欧米短期・ASEAN/アフリカ短期・博士号取得見込者）": "月額200,000円",
        "渡航費": "往復国際航空券（現物支給）",
        "渡日一時金": "定額200,000円（採用期間開始前から日本に居住実態がなく、かつ、採用期間が3か月以上の場合）",
        "その他": "海外旅行保険、一般は特別研究員奨励費に応募可能、欧米短期・ASEAN/アフリカ短期は調査研究費に申請可能"
      },
      "duration": {
        "一般": "12〜24ヶ月",
        "欧米短期": "1〜12ヶ月"
      },
      "eligibility": {
        "一般": "博士号取得後6年以内の外国人研究者（産休・育休期間は除外）",
        "欧米短期": "博士号取得後6年以内、または2年以内に博士号取得見込みの者。対象国：米国、カナダ、EU加盟国、英国、スイス、ノルウェー、ロシア"
      },
      "required_documents": [
        "申請書（電子申請システム）",
        "研究計画書",
        "推薦状",
        "博士学位証明書（または取得見込証明書）",
        "業績リスト",
        "受入研究者承諾書"
      ],
      "application_schedule": [
        {
          "intake": "2026年度（欧米短期・第1回）",
          "deadline": "2026年4月"
        },
        {
          "intake": "2026年度（欧米短期・第2回）",
          "deadline": "2026年8月"
        },
        {
          "intake": "2026年度（欧米短期・第3回）",
          "deadline": "2026年12月"
        },
        {
          "intake": "2026年度（一般・第1回）",
          "deadline": "2026年4月"
        },
        {
          "intake": "2026年度（一般・第2回）",
          "deadline": "2026年8月"
        }
      ],
      "url": "https://www.jsps.go.jp/j-fellow/",
      "related_urls": [
        {
          "label": "一般プログラム",
          "url": "https://www.jsps.go.jp/j-fellow/j-ippan/gaiyou.html"
        },
        {
          "label": "申請スケジュール（一般）",
          "url": "https://www.jsps.go.jp/j-fellow/j-ippan/boshu.html"
        },
        {
          "label": "欧米短期プログラム",
          "url": "https://www.jsps.go.jp/j-fellow/j-oubei-s/gaiyou.html"
        },
        {
          "label": "申請スケジュール（欧米短期）",
          "url": "https://www.jsps.go.jp/j-fellow/j-oubei-s/boshu.html"
        }
      ],
      "additional_urls": [
        "https://www.jsps.go.jp/j-fellow/j-ippan/boshu.html",
        "https://www.jsps.go.jp/j-fellow/j-oubei-s/boshu.html"
      ]
    },
    {
      "id": "mext_scholarship",
      "name": "文部科学省国費外国人留学生（研究留学生）",
      "name_en": "MEXT Scholarship (Research Student)",
      "organization": "文部科学省（MEXT）",
      "description": "日本政府が提供する外国人留学生向け奨学金制度。大使館推薦と大学推薦の2つの応募ルートがある。",
      "target_nationality": [
        "foreign"
      ],
      "current_education": [
        "bachelor",
        "master"
      ],
      "desired_path": [
        "master",
        "doctor"
      ],
      "tsukuba_related": false,
      "benefits": {
        "渡日旅費": "支給",
        "帰国旅費": "支給",
        "授業料": "国立大学は不徴収、公立・私立大学は国が負担",
        "入学料・検定料": "国立大学は不徴収、公立・私立大学は国が負担"
      },
      "duration": {
        "修士": "2年間（+予備教育期間）",
        "博士": "3年間（+予備教育期間）"
      },
      "eligibility": {
        "修士": "大学卒業者または卒業見込み者",
        "博士": "修士号取得者または取得見込み者",
        "年齢": "1991年4月2日以降に生まれた者（35歳未満）",
        "成績": "GPA 2.30以上（3.0スケール）"
      },
      "required_documents": [
        "申請書（所定様式）",
        "専攻分野及び研究計画書",
        "成績証明書",
        "卒業（修了）証明書",
        "推薦状",
        "言語能力証明書",
        "健康診断書"
      ],
      "application_schedule": [
        {
          "intake": "2027年度 大使館推薦（学部留学生・高等専門学校留学生・専修学校留学生）"
        },
        {
          "intake": "2027年度 大使館推薦（研究留学生）"
        },
        {
          "intake": "2026年度 大学推薦（日本語・日本文化研修留学生）"
        },
        {
          "intake": "2026年度 大学推薦（研究留学生・学部留学生（特別枠））"
        },
        {
          "intake": "2026年度 大学推薦（研究留学生・学部留学生（一般枠等））"
        },
        {
          "intake": "2026年度 大使館推薦（日本語・日本文化研修留学生及び教員研修留学生）"
        }
      ],
      "url": "https://www.mext.go.jp/a_menu/koutou/ryugaku/06032818.htm",
      "related_urls": [
        {
          "label": "2026年度募集要項（大使館推薦）",
          "url": "https://www.mext.go.jp/a_menu/koutou/ryugaku/boshu/1415352_00007.htm"
        },
        {
          "label": "Study in Japan",
          "url": "https://www.studyinjapan.go.jp/ja/planning/scholarships/mext-scholarships/"
        }
      ]
    },
    {
      "id": "tsukuba_graduate",
      "name": "筑波大学大学院 国際マテリアルズイノベーション学位プログラム（NIMS連携）",
      "name_en": "University of Tsukuba - Materials Innovation Program (NIMS Cooperative)",
      "organization": "筑波大学",
      "description": "筑波大学 数理物質科学研究群「国際マテリアルズイノベーション学位プログラム」。NIMSの研究者が指導教員として参画する連携大学院プログラム。NIMSジュニア研究員制度との併用が可能。入試は年度ごとに7月実施・10月実施・2月実施などの区分がある。",
      "target_nationality": [
        "japanese",
        "foreign"
      ],
      "current_education": [
        "bachelor",
        "master"
      ],
      "desired_path": [
        "master",
        "doctor"
      ],
      "tsukuba_related": true,
      "tsukuba_degree": [
        "master",
        "doctor"
      ],
      "benefits": {
        "入学料": "282,000円",
        "授業料（年額）": "535,800円（外国人留学生は608,800円）",
        "検定料": "30,000円"
      },
      "programs": [
        "応用理工学学位プログラム（電子・物理工学サブプログラム）",
        "応用理工学学位プログラム（物性・分子工学サブプログラム）",
        "応用理工学学位プログラム（NIMS連係 物質・材料工学サブプログラム）【博士後期のみ】",
        "国際マテリアルズイノベーション学位プログラム"
      ],
      "required_documents": [
        "卒業（見込）証明書",
        "学位取得（見込）証明書",
        "成績証明書",
        "Summary of Research and Future Research Plans",
        "Reference Letter（社会人特別選抜を除く）",
        "検定料収納証明書（コンビニエンスストア利用時）",
        "検定料のクレジットカード支払い申込内容照会結果画面のコピー（クレジットカード利用時）",
        "受験・就学承認書（該当者のみ）",
        "国費留学生証明書（該当者のみ）",
        "出願書類等提出明細票",
        "特定類型自己申告書（Web出願システムで入力）",
        "外部英語試験スコア票"
      ],
      "application_schedule": [
        {
          "intake": "2027年4月入学 7月実施（一般入学試験・社会人特別選抜）",
          "web_registration": "令和8年(2026年)5月22日(金)12時～6月1日(月)15時",
          "document_deadline": "令和8年(2026年)6月2日(火)",
          "university_contact_deadline": "令和8年(2026年)5月20日(水)",
          "exam_date": "令和8年(2026年)7月3日(金)～7月7日(火)",
          "result": "令和8年(2026年)7月21日(火)10時"
        },
        {
          "intake": "2027年4月入学 10月実施（一般入学試験・社会人特別選抜）",
          "web_registration": "令和8年(2026年)8月31日(月)12時～9月10日(木)15時",
          "document_deadline": "令和8年(2026年)9月11日(金)",
          "university_contact_deadline": "令和8年(2026年)8月25日(火)",
          "exam_date": "令和8年(2026年)10月8日(木)、10月13日(火)～15日(木)",
          "result": "令和8年(2026年)10月30日(金)10時"
        },
        {
          "intake": "2027年10月入学 10月実施（一般入学試験・社会人特別選抜）",
          "web_registration": "令和8年(2026年)8月31日(月)12時～9月10日(木)15時",
          "document_deadline": "令和8年(2026年)9月11日(金)",
          "university_contact_deadline": "令和8年(2026年)8月25日(火)",
          "exam_date": "令和8年(2026年)10月8日(木)、10月13日(火)～15日(木)",
          "result": "令和8年(2026年)10月30日(金)10時"
        }
      ],
      "url": "https://www.ap-graduate.tsukuba.ac.jp/course/pas/",
      "related_urls": [
        {
          "label": "入試スケジュール",
          "url": "https://www.tsukuba.ac.jp/admission/graduate-overview/information/"
        },
        {
          "label": "NIMS大学院プログラム",
          "url": "https://www.nims.go.jp/students/program/"
        },
        {
          "label": "数理物質科学研究群",
          "url": "https://www.ap-graduate.tsukuba.ac.jp/course/pas/"
        }
      ],
      "focus_program": "国際マテリアルズイノベーション学位プログラム",
      "additional_urls": [
        "https://www.ap-graduate.tsukuba.ac.jp/course/pas/first_all/",
        "https://www.ap-graduate.tsukuba.ac.jp/course/pas/second_all/"
      ]
    },
    {
      "id": "nims_icys",
      "name": "NIMS ICYS リサーチフェロー",
      "name_en": "NIMS ICYS Research Fellow",
      "organization": "NIMS 若手国際研究センター（ICYS）",
      "description": "博士取得後の若手研究者を対象とした独立研究者育成プログラム。NIMSの先端研究施設を利用しながら独立した研究を追求できる。NIMS定年制研究員への優遇措置あり（約5割採用）。",
      "target_nationality": [
        "japanese",
        "foreign"
      ],
      "current_education": [
        "doctor"
      ],
      "desired_path": [
        "postdoc"
      ],
      "tsukuba_related": false,
      "benefits": {
        "ICYS PI 研究費": "年間400万円",
        "ICYS Research Fellow 研究費": "年間200万円",
        "給与": "Competitive salary"
      },
      "duration": {
        "初期": "3年間",
        "最長": "5年（評価により1年毎更新）"
      },
      "eligibility": {
        "ポスドク": "博士号取得後10年以内、または着任までに取得見込みの者。国籍不問"
      },
      "required_documents": [
        "応募書類（Application Form、研究提案含む、MS-Word）",
        "履歴書（CV、PDF）",
        "博士学位証明書または取得見込証明書（PDF）",
        "代表的な論文3編（PDF）",
        "出版論文のDOIリスト（MS-Excel）"
      ],
      "application_schedule": [
        {
          "intake": "2026年度採用（2025年秋期公募）",
          "application_start": "2025年9月2日",
          "deadline": "2025年10月29日必着",
          "document_screening": "2025年11月頃",
          "interview": "2025年11月〜12月頃",
          "result": "2025年12月頃",
          "adoption_period": "2026年4月1日〜9月1日着任",
          "note": "書類選考後、面接審査。英語で応募書類作成。icys-recruit@nims.go.jp にメール提出"
        },
        {
          "intake": "2026年度採用（2026年春期公募）",
          "application_start": "2026年2月頃",
          "deadline": "2026年3月24日必着",
          "result": "2026年6月頃",
          "adoption_period": "2026年10月1日以降着任",
          "note": "書類選考後、面接審査。テキストモードのメールで提出（HTMLメール不可）"
        },
        {
          "intake": "2027年度採用（2026年秋期公募）",
          "application_start": "2026年9月頃",
          "deadline": "2026年10月下旬",
          "result": "2026年12月頃",
          "adoption_period": "2027年4月1日以降着任",
          "note": "書類選考後、面接審査"
        },
        {
          "intake": "随時採用（米国滞在者向け特別公募）",
          "application_start": "随時",
          "deadline": "随時受付",
          "result": "申請後約2ヶ月",
          "note": "米国滞在若手研究者向け特別枠、Applications accepted at any time"
        }
      ],
      "url": "https://www.nims.go.jp/icys/",
      "related_urls": [
        {
          "label": "採用情報",
          "url": "https://www.nims.go.jp/icys/recruitment/"
        },
        {
          "label": "応募書類ダウンロード",
          "url": "https://www.nims.go.jp/icys/recruitment/application.html"
        },
        {
          "label": "ICYSについて",
          "url": "https://www.nims.go.jp/icys/about/"
        },
        {
          "label": "NIMS採用情報",
          "url": "https://www.nims.go.jp/employment/"
        },
        {
          "label": "JREC-IN募集情報",
          "url": "https://jrecin.jst.go.jp/seek/SeekJorDetail?id=D125090152"
        }
      ]
    },
    {
      "id": "nims_icgp",
      "name": "NIMS ICGP（国際共同大学院プログラム）",
      "name_en": "NIMS International Cooperative Graduate Program (ICGP)",
      "organization": "NIMS（物質・材料研究機構）",
      "description": "NIMSとICGP協定を締結した海外大学の大学院生が、NIMSで6〜12ヶ月間の学位研究を行うプログラム。NIMS研究者が共同指導教員として学位論文を共同指導する。45機関（アジア・オセアニア29、欧州14、米州2）と協定締結済。",
      "target_nationality": [
        "foreign"
      ],
      "current_education": [
        "master",
        "doctor"
      ],
      "desired_path": [
        "doctor"
      ],
      "tsukuba_related": false,
      "benefits": {
        "Financial support": "NIMS provides living allowance and accommodation fee in Tsukuba",
        "Accommodation": "Ninomiya House",
        "Visa": "Arrangements supported by NIMS",
        "Support": "Technical/administrative support in English at NIMS, Daily-life support service"
      },
      "duration": {
        "標準": "6〜12ヶ月（複数回に分割可能、事前調整要）"
      },
      "eligibility": {
        "対象": "ICGP協定大学の正規大学院生（博士課程推奨）",
        "条件": "滞在期間中を通じて在籍していること",
        "言語": "英語必須、日本語不要（あれば有利）",
        "定員": "各大学あたり年間2名"
      },
      "required_documents": [
        "Application documents (provided to the partner universities before the application period starts)"
      ],
      "application_schedule": [
        {
          "intake": "2026年度",
          "application_start": "2026年9月",
          "note": "Application period is held one to three times a year, depending on the year"
        }
      ],
      "url": "https://www.nims.go.jp/students/en/international/",
      "related_urls": [
        {
          "label": "ICGP制度概要（英語）",
          "url": "https://www.nims.go.jp/eng/hr-development/ICGP.html"
        },
        {
          "label": "応募手続き",
          "url": "https://www.nims.go.jp/students/en/application/"
        },
        {
          "label": "協定大学一覧",
          "url": "https://www.nims.go.jp/eng/research/collaboration/joint-graduate.html"
        },
        {
          "label": "研究者総覧SAMURAI",
          "url": "https://samurai.nims.go.jp/"
        }
      ]
    }
  ],
  "last_updated": "2026-06-22"
}
